cadorchestrator/ConfigOptionsSchema.json
cadorchestrator/__init__.py
cadorchestrator/__main__.py
cadorchestrator/components.py
cadorchestrator/exceptions.py
cadorchestrator/generate.py
cadorchestrator/settings.py
cadorchestrator/utilities.py
cadorchestrator/server/README.md
cadorchestrator/server/__init__.py
cadorchestrator/server/dockerfile
cadorchestrator/server/server.py
cadorchestrator/server/app/index.html
cadorchestrator/server/app/assets/index-BjKy5Qxx.css
cadorchestrator/server/app/assets/index-C2DBC1G_.js
cadorchestrator/server/app/assets/model-viewer-CePoBgTL.js
cadorchestrator/server/app/static/images/CadOrchestrator.png
cadorchestrator/server/app/static/images/favicon.png
cadorchestrator-0.1.0.dist-info/METADATA
cadorchestrator-0.1.0.dist-info/WHEEL
cadorchestrator-0.1.0.dist-info/entry_points.txt
cadorchestrator-0.1.0.dist-info/licenses/LICENSE
cadorchestrator-0.1.0.dist-info/RECORD
