Metadata-Version: 2.3
Name: cadorchestrator
Version: 0.1.0
Summary: CadOrchestrator helps you create consistent production files and clear assembly documentation for your modular hardware project.
Author: Andreas Kahler, Jeremy Wright
Author-email: Julian Stirling <julian@julianstirling.co.uk>
Keywords: CAD,configuration,documentation,hardware
Classifier: License :: OSI Approved :: GNU General Public License v3 (GPLv3)
Requires-Python: >=3.10
Requires-Dist: exsource-tools>=0.0.7
Requires-Dist: fastapi>=0.109.1
Requires-Dist: gitbuilding>=0.15.0a3
Requires-Dist: gunicorn
Requires-Dist: orjson
Requires-Dist: uvicorn[standard]<0.24.0,>=0.23.2
Provides-Extra: dev
Requires-Dist: colorama; extra == 'dev'
Requires-Dist: json-schema-for-humans; extra == 'dev'
Requires-Dist: pdoc; extra == 'dev'
Requires-Dist: pylint; extra == 'dev'
